setup.py
django_nonrel_enuff.egg-info/PKG-INFO
django_nonrel_enuff.egg-info/SOURCES.txt
django_nonrel_enuff.egg-info/dependency_links.txt
django_nonrel_enuff.egg-info/top_level.txt
enuff/__init__.py
enuff/managers.py
enuff/models.py
enuff/tests.py
enuff/utils.py
enuff/views.py
enuff/backends/__init__.py
enuff/backends/redis.py