Metadata-Version: 1.0
Name: django-nonrel-enuff
Version: 0.1
Summary: Crutch for SQL users
Home-page: http://github.com/subsume/django-nonrel-enuff
Author: Steve Yeago
Author-email: subsume@gmail.com
License: UNKNOWN
Platform: UNKNOWN
Classifier: Framework :: Django
Classifier: Intended Audience :: Developers
Classifier: Intended Audience :: System Administrators
Classifier: Operating System :: OS Independent
Classifier: Topic :: Software Development
